pip_command
