Metadata-Version: 2.1
Name: pip-command
Version: 0.1.3
Summary: lib for fast work with pip commands
Home-page: https://github.com/pavelglazunov/pip-command
Author: pavelgs
Author-email: p6282813@yandex.ru
License: Apache License, Version 2.0, see LICENSE file
Platform: UNKNOWN
